setup.cfg
setup.py
hulkify/__init__.py
hulkify/grammar.json
hulkify/hulkify.py
hulkify.egg-info/PKG-INFO
hulkify.egg-info/SOURCES.txt
hulkify.egg-info/dependency_links.txt
hulkify.egg-info/requires.txt
hulkify.egg-info/top_level.txt