Metadata-Version: 1.1
Name: hulkify
Version: 0.0.8
Summary: Turn normal English into HULK-SPEAK
Home-page: https://github.com/sjml/hulkify
Author: Shane Liesegang
Author-email: shane@techie.net
License: MIT
Keywords: hulk english text filter
Platform: UNKNOWN
Classifier: Development Status :: 3 - Alpha
Classifier: Intended Audience :: Developers
Classifier: License :: OSI Approved :: MIT License
Classifier: Natural Language :: English
Classifier: Programming Language :: Python :: 2 :: Only
Classifier: Programming Language :: Python :: 2.7
Classifier: Topic :: Text Processing :: Filters
